journalview/__init__.py
journalview/cli.py
journalview/journalctl.py
journalview-0.2.0.dist-info/licenses/LICENSE
journalview-0.2.0.dist-info/METADATA
journalview-0.2.0.dist-info/WHEEL
journalview-0.2.0.dist-info/entry_points.txt
journalview-0.2.0.dist-info/top_level.txt
journalview-0.2.0.dist-info/RECORD
