Metadata-Version: 2.4
Name: journalview
Version: 0.2.0
Summary: Python package to monitor and profile linux journal boot sequence
Author-email: FroykeFroyke <froykefroyke@gmail.com>
License: MIT
Project-URL: Homepage, https://github.com/froykefroyke/journalview
Requires-Python: >=3.9
License-File: LICENSE
Requires-Dist: rich
Requires-Dist: trogon
Requires-Dist: click
Dynamic: license-file
